csscade/__init__.py
csscade/merger.py
csscade/models.py
csscade/performance.py
csscade/property_merger.py
csscade/property_merger_backup.py
csscade/property_merger_enhanced.py
csscade/property_merger_full_expand.py
csscade/property_merger_hybrid.py
csscade/property_merger_old.py
csscade/cache/__init__.py
csscade/cache/lru_cache.py
csscade/combinator/__init__.py
csscade/combinator/combinator.py
csscade/combinator/conflict_detector.py
csscade/combinator/css_analyzer.py
csscade/combinator/property_groups.py
csscade/config/__init__.py
csscade/config/config_manager.py
csscade/debug/__init__.py
csscade/debug/debugger.py
csscade/generator/__init__.py
csscade/generator/naming.py
csscade/generator/output.py
csscade/handlers/__init__.py
csscade/handlers/error_recovery.py
csscade/handlers/fallback.py
csscade/handlers/large_file_handler.py
csscade/handlers/media.py
csscade/handlers/selector_parser.py
csscade/handlers/selector_utils.py
csscade/handlers/shorthand.py
csscade/handlers/shorthand_hybrid.py
csscade/handlers/unicode_handler.py
csscade/handlers/variables.py
csscade/integration/__init__.py
csscade/integration/helpers.py
csscade/optimization/__init__.py
csscade/optimization/batch_processor.py
csscade/optimization/deduplicator.py
csscade/parser/__init__.py
csscade/parser/css_parser.py
csscade/parser/value_parser.py
csscade/resolvers/__init__.py
csscade/resolvers/conflict_detector.py
csscade/strategies/__init__.py
csscade/strategies/base.py
csscade/strategies/component.py
csscade/strategies/permanent.py
csscade/strategies/replace.py
csscade/utils/__init__.py
csscade/utils/exceptions.py
csscade/utils/important_parser.py
csscade/utils/rule_matcher.py
csscade/validation/__init__.py
csscade/validation/browser_compat.py
csscade/validation/security.py
csscade/validation/syntax_validator.py
csscade/validators/__init__.py
csscade-0.3.0.dist-info/licenses/LICENSE
csscade-0.3.0.dist-info/METADATA
csscade-0.3.0.dist-info/WHEEL
csscade-0.3.0.dist-info/top_level.txt
csscade-0.3.0.dist-info/RECORD
