Metadata-Version: 2.4
Name: csscade
Version: 0.3.0
Summary: Intelligent CSS merging with conflict resolution and multiple strategies
Author: sebieire
Maintainer: sebieire
License: MIT
Project-URL: Homepage, https://github.com/sebieire/csscade
Project-URL: Repository, https://github.com/sebieire/csscade
Project-URL: Issues, https://github.com/sebieire/csscade/issues
Project-URL: Documentation, https://github.com/sebieire/csscade#readme
Keywords: css,merge,conflict-resolution,styling,theme,customization
Classifier: Development Status :: 4 - Beta
Classifier: Intended Audience :: Developers
Classifier: License :: OSI Approved :: MIT License
Classifier: Programming Language :: Python :: 3
Classifier: Programming Language :: Python :: 3.7
Classifier: Programming Language :: Python :: 3.8
Classifier: Programming Language :: Python :: 3.9
Classifier: Programming Language :: Python :: 3.10
Classifier: Programming Language :: Python :: 3.11
Classifier: Programming Language :: Python :: 3.12
Classifier: Topic :: Software Development :: Libraries :: Python Modules
Classifier: Topic :: Text Processing :: Markup
Classifier: Topic :: Software Development :: User Interfaces
Requires-Python: >=3.7
License-File: LICENSE
Requires-Dist: cssutils>=2.11.1
Provides-Extra: dev
Requires-Dist: pytest>=8.0.0; extra == "dev"
Requires-Dist: black>=25.0.0; extra == "dev"
Requires-Dist: mypy>=1.17.0; extra == "dev"
Requires-Dist: ruff>=0.12.0; extra == "dev"
Dynamic: license-file
